DESfiddle/__init__.py
DESfiddle/utils.py
DESfiddle-1.0.0.dist-info/LICENSE
DESfiddle-1.0.0.dist-info/METADATA
DESfiddle-1.0.0.dist-info/WHEEL
DESfiddle-1.0.0.dist-info/top_level.txt
DESfiddle-1.0.0.dist-info/RECORD
