Metadata-Version: 2.1
Name: DESfiddle
Version: 1.0.0
Summary: A python package that offers high flexibility for implementing and experimenting with non-classical DES.
Home-page: https://github.com/dilbwagsingh/DESfiddle
Author: Dilbwag Singh
Author-email: dilbwagsingh.che18@iitbhu.ac.in
License: UNKNOWN
Keywords: python,DES,Data Encryption Standard,DEA,Data Encryption Algorithm
Platform: UNKNOWN
Classifier: Development Status :: 1 - Planning
Classifier: Intended Audience :: Developers
Classifier: Intended Audience :: Education
Classifier: Intended Audience :: End Users/Desktop
Classifier: Intended Audience :: Information Technology
Classifier: Intended Audience :: Legal Industry
Classifier: Intended Audience :: Science/Research
Classifier: Topic :: Scientific/Engineering :: Mathematics
Classifier: Topic :: Security
Classifier: Topic :: Security :: Cryptography
Classifier: Topic :: Software Development
Classifier: Topic :: Software Development :: Libraries
Classifier: Topic :: Software Development :: Libraries :: Python Modules
Classifier: Topic :: Utilities
Classifier: License :: OSI Approved :: MIT License
Classifier: Programming Language :: Python :: 3
Classifier: Programming Language :: Python :: 3.6
Classifier: Programming Language :: Python :: 3.7
Classifier: Programming Language :: Python :: 3.8
Classifier: Programming Language :: Python :: 3.9
Classifier: Programming Language :: Python :: 3.10
Classifier: Operating System :: OS Independent
Classifier: Natural Language :: English
Requires-Python: >=3.5.0
